calra_lambda/__init__.py
calra_lambda/decorators.py
calra_lambda-0.1.0.dist-info/LICENSE
calra_lambda-0.1.0.dist-info/METADATA
calra_lambda-0.1.0.dist-info/WHEEL
calra_lambda-0.1.0.dist-info/top_level.txt
calra_lambda-0.1.0.dist-info/RECORD
