Metadata-Version: 2.1
Name: calra-lambda
Version: 0.1.0
Summary: CDK Ast Lambda Rest Api - Lambda Package
Author-email: Mateo Marcos <calra.github+mateo@gmail.com>, Emanuel Arguinarena <calra.github+emanuel@gmail.com>, Lucas Picchi <calra.github+lucas@gmail.com>
License: MIT License
Project-URL: Bug Reports, https://github.com/cdk-ast-lambda-rest-api/calra-lambda/issues
Project-URL: Source, https://github.com/cdk-ast-lambda-rest-api/calra-lambda
Keywords: cdk,lambda,aws,api gateway,ast,decorators
Classifier: Development Status :: 2 - Pre-Alpha
Classifier: Intended Audience :: Developers
Classifier: Framework :: AWS CDK :: 2
Classifier: Topic :: Software Development :: Libraries :: Python Modules
Classifier: Topic :: Software Development :: Build Tools
Classifier: License :: OSI Approved :: MIT License
Classifier: Programming Language :: Python :: 3.9
Classifier: Programming Language :: Python :: 3.10
Classifier: Programming Language :: Python :: 3.11
Classifier: Programming Language :: Python :: 3.12
Requires-Python: >=3.9
License-File: LICENSE
